aviro/__init__.py
aviro/span.py
aviro-0.1.5.dist-info/licenses/LICENSE
aviro-0.1.5.dist-info/METADATA
aviro-0.1.5.dist-info/WHEEL
aviro-0.1.5.dist-info/top_level.txt
aviro-0.1.5.dist-info/RECORD
